{
  "series": [
    {
      "name": "Revenue",
      "data": [
        {"x": "Jan", "y": 12000},
        {"x": "Feb", "y": 19000},
        {"x": "Mar", "y": 15000},
        {"x": "Apr", "y": 25000},
        {"x": "May", "y": 22000},
        {"x": "Jun", "y": 30000}
      ],
      "color": "#3b82f6"
    },
    {
      "name": "Expenses",
      "data": [
        {"x": "Jan", "y": 8000},
        {"x": "Feb", "y": 12000},
        {"x": "Mar", "y": 10000},
        {"x": "Apr", "y": 14000},
        {"x": "May", "y": 13000},
        {"x": "Jun", "y": 16000}
      ],
      "color": "#ef4444"
    }
  ],
  "x_label": "Month",
  "y_label": "Amount ($)"
}
